exoplanet/__init__.py
exoplanet/citations.py
exoplanet/compat.py
exoplanet/estimators.py
exoplanet/exoplanet_version.py
exoplanet/interp.py
exoplanet/units.py
exoplanet/utils.py
exoplanet/distributions/__init__.py
exoplanet/distributions/distributions.py
exoplanet/distributions/eccentricity.py
exoplanet/light_curves/__init__.py
exoplanet/light_curves/interpolated.py
exoplanet/light_curves/limb_dark.py
exoplanet/light_curves/secondary_eclipse.py
exoplanet/orbits/__init__.py
exoplanet/orbits/constants.py
exoplanet/orbits/dur_to_ecc.py
exoplanet/orbits/keplerian.py
exoplanet/orbits/simple.py
exoplanet/orbits/ttv.py
exoplanet-0.6.0.dist-info/LICENSE
exoplanet-0.6.0.dist-info/METADATA
exoplanet-0.6.0.dist-info/WHEEL
exoplanet-0.6.0.dist-info/top_level.txt
exoplanet-0.6.0.dist-info/RECORD
