Metadata-Version: 2.1
Name: exoplanet
Version: 0.6.0
Summary: Fast and scalable MCMC for all your exoplanet needs
Home-page: https://docs.exoplanet.codes
Author: Daniel Foreman-Mackey
Author-email: foreman.mackey@gmail.com
Maintainer: Daniel Foreman-Mackey
Maintainer-email: foreman.mackey@gmail.com
License: MIT
Classifier: Development Status :: 4 - Beta
Classifier: Intended Audience :: Developers
Classifier: Intended Audience :: Science/Research
Classifier: License :: OSI Approved :: MIT License
Classifier: Operating System :: OS Independent
Classifier: Programming Language :: Python
Classifier: Programming Language :: Python :: 3
Requires-Python: >=3.6
License-File: LICENSE
Requires-Dist: astropy>=3.1
Provides-Extra: pymc3
Requires-Dist: pymc3>=3.9; extra == "pymc3"
Requires-Dist: numpy<1.22; extra == "pymc3"
Requires-Dist: aesara-theano-fallback>=0.0.2; extra == "pymc3"
Requires-Dist: xarray<2023.10.0; extra == "pymc3"
Requires-Dist: exoplanet-core>=0.2.0; extra == "pymc3"
Provides-Extra: pymc
Requires-Dist: pymc>=5.0.0; extra == "pymc"
Requires-Dist: exoplanet-core>=0.3.0; extra == "pymc"
Provides-Extra: extras
Requires-Dist: pymc>=5.0.0; extra == "extras"
Requires-Dist: pymc-ext>=1.0.1; extra == "extras"
Requires-Dist: celerite2>=0.3.1; extra == "extras"
Provides-Extra: extras-pymc3
Requires-Dist: pymc3>=3.9; extra == "extras-pymc3"
Requires-Dist: pymc3-ext>=0.1.0; extra == "extras-pymc3"
Requires-Dist: celerite2<0.3.1,>=0.2.0; extra == "extras-pymc3"
Provides-Extra: test
Requires-Dist: scipy; extra == "test"
Requires-Dist: pytest; extra == "test"
Requires-Dist: pytest-env; extra == "test"
Provides-Extra: docs
Requires-Dist: exoplanet-core>=0.3.0; extra == "docs"
Requires-Dist: pymc>=5.0.0; extra == "docs"
Requires-Dist: pymc-ext>=1.0.1; extra == "docs"
Requires-Dist: sphinx-book-theme; extra == "docs"
Requires-Dist: myst-nb; extra == "docs"
Requires-Dist: ipython; extra == "docs"
Requires-Dist: matplotlib; extra == "docs"
Requires-Dist: corner; extra == "docs"
Requires-Dist: emcee; extra == "docs"
